intersectlib/__init__.py
intersectlib/intersectlib_code.py
intersectlib-1.3.2.dist-info/METADATA
intersectlib-1.3.2.dist-info/WHEEL
intersectlib-1.3.2.dist-info/licenses/LICENSE
intersectlib-1.3.2.dist-info/RECORD
