Metadata-Version: 2.1
Name: intersectlib
Version: 1.3.2
Summary: A package that finds range intersections and remainders
Project-URL: Homepage, https://github.com/Rducker0208/intersectlib
Project-URL: Issues, https://github.com/Rducker0208/intersectlib/issues
Author-email: Ricardo Ducker <duckerricardo@gmail.com>
License-File: LICENSE
Keywords: destinations,intersections,ranges,remainders,sources
Classifier: License :: OSI Approved :: MIT License
Classifier: Operating System :: OS Independent
Classifier: Programming Language :: Python :: 3
Requires-Python: >=3.8
